{
  "[Something] falling like a rock": "Dropping [something]",
  "[Something] falling like a feather or paper": "Dropping [something]",
  "Throwing [something]": "Dropping [something]",
  "Throwing [something] onto a surface": "Dropping [something]",
  "Throwing [something] in the air and letting it fall": "Dropping [something]",
  "Pushing [something] from right to left": "Moving [something] from right to left",
  "Pulling [something] from right to left": "Moving [something] from right to left",
  "Pulling [something] from left to right": "Moving [something] from left to right",
  "Pushing [something] from left to right": "Moving [something] from left to right",
  "Picking [something] up": "Picking [something] up",
  "Lifting [something] up completely without letting it drop down": "Picking [something] up",
  "Moving [something] up": "Picking [something] up",
  "Lifting [something] with [something] on it": "Picking [something] up",
  "Taking [something] from [somewhere]": "Picking [something] up",
  "Taking [one of many similar things on the table]": "Picking [something] up",
  "Taking [something] out of [something]": "Picking [something] up",
  "Putting [something] next to [something]": "Putting [something]",
  "Putting [something] onto [something]": "Putting [something]",
  "Putting [something] on a surface": "Putting [something]",
  "Putting [something similar to other things that are already on the table]": "Putting [something]",
  "Putting [something] behind [something]": "Putting [something]",
  "Putting [something], [something] and [something] on the table": "Putting [something]",
  "Putting [something] and [something] on the table": "Putting [something]",
  "Putting [something] on a flat surface without letting it roll": "Putting [something]",
  "Putting [something] that can’t roll onto a slanted surface, so it stays where it is": "Putting [something]",
  "Poking [something] so that it falls over": "Poking [something]",
  "Poking [something] so lightly that it doesn't or almost doesn't move": "Poking [something]",
  "Poking a stack of [something] so the stack collapses": "Poking [something]",
  "Poking a stack of [something] without the stack collapsing": "Poking [something]",
  "Tearing [something] into two pieces": "Tearing [something]",
  "Tearing [something] just a little bit": "Tearing [something]",
  "Pouring [something] into [something]": "Pouring [something]",
  "Pouring [something] onto [something]": "Pouring [something]",
  "Pouring [something] out of [something]": "Pouring [something]",
  "Pouring [something] into [something] until it overflows": "Pouring [something]",
  "Trying to pour [something] into [something], but missing so it spills next to it": "Pouring [something]",
  "Holding [something]": "Holding [something]",
  "Holding [something] in front of [something]": "Holding [something]",
  "Showing [something] on top of [something]": "Showing [something] (almost no hand)",
  "Showing [something] behind [something]": "Showing [something] (almost no hand)",
  "Showing [something] next to [something]": "Showing [something] (almost no hand)"
}